django_settings_env/__init__.py
django_settings_env/deferred.py
django_settings_env/env_django.py
django_settings_env/parser/__init__.py
django_settings_env/plugin/__init__.py
django_settings_env/plugin/plugin_cache.py
django_settings_env/plugin/plugin_database.py
django_settings_env/plugin/plugin_email.py
django_settings_env/plugin/plugin_queue.py
django_settings_env/plugin/plugin_search.py
django_settings_env/plugin/plugin_tasks.py
django_settings_env-5.6.0.dist-info/licenses/LICENSE.md
django_settings_env-5.6.0.dist-info/WHEEL
django_settings_env-5.6.0.dist-info/METADATA
django_settings_env-5.6.0.dist-info/RECORD
