Metadata-Version: 2.4
Name: django-settings-env
Version: 5.6.0
Summary: 12-factor.net settings handler for Django
Author-email: David Nugent <davidn@uniquode.io>
Requires-Python: >=3.11
Classifier: Programming Language :: Python :: 3.11
Classifier: Programming Language :: Python :: 3.12
Classifier: Programming Language :: Python :: 3.13
Classifier: Framework :: Django :: 4.2
Classifier: Framework :: Django :: 5.0
Classifier: Framework :: Django :: 5.1
Classifier: Framework :: Django :: 5.2
License-File: LICENSE.md
Requires-Dist: django>=5.0
Requires-Dist: envex>=4.2
Requires-Dist: yarl>=1.18.3
Requires-Dist: django-class-settings>=0.2 ; extra == "extras"
Requires-Dist: hvac>=1.1.1 ; extra == "vault"
Project-URL: homepage, https://github.com/deeprave/django-settings-env
Project-URL: repository, https://github.com/deeprave/django-settings-env
Provides-Extra: extras
Provides-Extra: vault
